sp_storage/__init__.py
sp_storage/sharepoint.py
sp_storage-0.0.1.dist-info/LICENSE
sp_storage-0.0.1.dist-info/METADATA
sp_storage-0.0.1.dist-info/WHEEL
sp_storage-0.0.1.dist-info/top_level.txt
sp_storage-0.0.1.dist-info/RECORD
