Metadata-Version: 2.1
Name: sp-storage
Version: 0.0.1
Summary: Storage provider for sharepoint service
Author-email: Sungwon Um <shineum@gmail.com>
License: The MIT License (MIT)
Project-URL: Homepage, https://github.com/shineum/sp_storage
Keywords: storage,sharepoint
Classifier: License :: OSI Approved :: MIT License
Classifier: Programming Language :: Python
Classifier: Programming Language :: Python :: 3
Requires-Python: >=3.7
License-File: LICENSE
Requires-Dist: django-storages (>=1.10.0)
Requires-Dist: Office365-REST-Python-Client (>=2.3.10)
